gybe/__init__.py
gybe/decorators.py
gybe/exceptions.py
gybe/modeling.py
gybe/py.typed
gybe/yaml.py
gybe/codegen/__init__.py
gybe/codegen/__main__.py
gybe/codegen/cli.py
gybe/codegen/k8s_modules.py
gybe/k8s/__init__.py
gybe/k8s/types.py
gybe/k8s/v1_31/__init__.py
gybe/k8s/v1_31/admissionregistration/v1.py
gybe/k8s/v1_31/admissionregistration/v1alpha1.py
gybe/k8s/v1_31/admissionregistration/v1beta1.py
gybe/k8s/v1_31/api/resource.py
gybe/k8s/v1_31/apiextensions/v1.py
gybe/k8s/v1_31/apiregistration/v1.py
gybe/k8s/v1_31/apiserverinternal/v1alpha1.py
gybe/k8s/v1_31/apps/v1.py
gybe/k8s/v1_31/authentication/v1.py
gybe/k8s/v1_31/authentication/v1alpha1.py
gybe/k8s/v1_31/authentication/v1beta1.py
gybe/k8s/v1_31/authorization/v1.py
gybe/k8s/v1_31/autoscaling/v1.py
gybe/k8s/v1_31/autoscaling/v2.py
gybe/k8s/v1_31/batch/v1.py
gybe/k8s/v1_31/certificates/v1.py
gybe/k8s/v1_31/certificates/v1alpha1.py
gybe/k8s/v1_31/coordination/v1.py
gybe/k8s/v1_31/coordination/v1alpha1.py
gybe/k8s/v1_31/coordination/v1alpha2.py
gybe/k8s/v1_31/core/v1.py
gybe/k8s/v1_31/discovery/v1.py
gybe/k8s/v1_31/events/v1.py
gybe/k8s/v1_31/flowcontrol/v1.py
gybe/k8s/v1_31/flowcontrol/v1beta3.py
gybe/k8s/v1_31/meta/v1.py
gybe/k8s/v1_31/networking/v1.py
gybe/k8s/v1_31/networking/v1beta1.py
gybe/k8s/v1_31/node/v1.py
gybe/k8s/v1_31/pkg/version.py
gybe/k8s/v1_31/policy/v1.py
gybe/k8s/v1_31/rbac/v1.py
gybe/k8s/v1_31/resource/v1alpha3.py
gybe/k8s/v1_31/resource/v1beta1.py
gybe/k8s/v1_31/scheduling/v1.py
gybe/k8s/v1_31/storage/v1.py
gybe/k8s/v1_31/storage/v1alpha1.py
gybe/k8s/v1_31/storage/v1beta1.py
gybe/k8s/v1_31/storagemigration/v1alpha1.py
gybe/k8s/v1_31/util/intstr.py
gybe/k8s/v1_32/__init__.py
gybe/k8s/v1_32/admissionregistration/v1.py
gybe/k8s/v1_32/admissionregistration/v1alpha1.py
gybe/k8s/v1_32/admissionregistration/v1beta1.py
gybe/k8s/v1_32/api/resource.py
gybe/k8s/v1_32/apiextensions/v1.py
gybe/k8s/v1_32/apiregistration/v1.py
gybe/k8s/v1_32/apiserverinternal/v1alpha1.py
gybe/k8s/v1_32/apps/v1.py
gybe-0.7.0.dist-info/METADATA
gybe-0.7.0.dist-info/WHEEL
gybe-0.7.0.dist-info/licenses/LICENSE
gybe-0.7.0.dist-info/RECORD
