Metadata-Version: 2.4
Name: gybe
Version: 0.7.0
Project-URL: Documentation, https://github.com/petermorrowdev/gybe#readme
Project-URL: Issues, https://github.com/petermorrowdev/gybe/issues
Project-URL: Source, https://github.com/petermorrowdev/gybe
Author-email: Peter Morrow <petermorrowtech@gmail.com>
License-Expression: MIT
License-File: LICENSE
Classifier: Development Status :: 4 - Beta
Classifier: Programming Language :: Python
Classifier: Programming Language :: Python :: 3.8
Classifier: Programming Language :: Python :: 3.9
Classifier: Programming Language :: Python :: 3.10
Classifier: Programming Language :: Python :: 3.11
Classifier: Programming Language :: Python :: 3.12
Classifier: Programming Language :: Python :: Implementation :: CPython
Classifier: Programming Language :: Python :: Implementation :: PyPy
Requires-Python: >=3.10
Requires-Dist: attrs
Requires-Dist: cattrs
Requires-Dist: click>=7.0.0
Requires-Dist: pyyaml>=5.0.0
Provides-Extra: test
Requires-Dist: coverage[toml]>=6.5; extra == 'test'
Requires-Dist: mypy; extra == 'test'
Requires-Dist: pytest; extra == 'test'
Requires-Dist: pytest-cov; extra == 'test'
Requires-Dist: ruff; extra == 'test'
Requires-Dist: types-pyyaml; extra == 'test'
